setup.py
subscene/__init__.py
subscene_api.egg-info/PKG-INFO
subscene_api.egg-info/SOURCES.txt
subscene_api.egg-info/dependency_links.txt
subscene_api.egg-info/top_level.txt