Metadata-Version: 1.1
Name: subscene-api
Version: 1.0.0
Summary: python wrapper for Subscene subtitle database.
Home-page: https://github.com/mamins1376/Subscene-API
Author: Mohammad Amin Sameti
Author-email: mamins1376@gmail.com
License: GNU General Public License v3 or later
Keywords: subscene api wrapper python3
Platform: UNKNOWN
Classifier: License :: OSI Approved :: GNU General Public License v3 or later (GPLv3+)
Classifier: Topic :: Software Development
Classifier: Topic :: Internet :: WWW/HTTP
Classifier: Programming Language :: Python :: 3
Classifier: Operating System :: OS Independent
Classifier: Development Status :: 5 - Production/Stable
